tagra/__init__.py
tagra/analysis.py
tagra/config.py
tagra/graph.py
tagra/preprocessing.py
tagra/utils.py
tests/__init__.py
tests/test_analysis.py
tests/test_config.py
tests/test_graph.py
tests/test_preprocessing.py
tests/tests.py
TaGra-1.0.0.dist-info/LICENSE
TaGra-1.0.0.dist-info/METADATA
TaGra-1.0.0.dist-info/WHEEL
TaGra-1.0.0.dist-info/entry_points.txt
TaGra-1.0.0.dist-info/top_level.txt
TaGra-1.0.0.dist-info/RECORD
