Metadata-Version: 2.1
Name: TaGra
Version: 1.0.0
Summary: TaGra: TAbular data preprocessing to GRAph representation.
Home-page: https://github.com/davidetorre92/TaGra
Author: Davide Torre, Davide Chicco
Author-email: davidetorre92@gmail.com
License: UNKNOWN
Platform: UNKNOWN
Classifier: Programming Language :: Python :: 3
Classifier: License :: OSI Approved :: MIT License
Classifier: Operating System :: OS Independent
Requires-Python: >=3.10
License-File: LICENSE
Requires-Dist: matplotlib
Requires-Dist: networkx
Requires-Dist: numpy
Requires-Dist: pandas
Requires-Dist: plotly
Requires-Dist: scikit-learn
